easyneuron/__init__.py
easyneuron/_classes/__init__.py
easyneuron/_classes/models.py
easyneuron/_testutils/__init__.py
easyneuron/_testutils/gh_actions.py
easyneuron/_testutils/logger.py
easyneuron/agents/__init__.py
easyneuron/agents/envs/__init__.py
easyneuron/agents/envs/_classes.py
easyneuron/agents/envs/examples.py
easyneuron/agents/qlearn/__init__.py
easyneuron/agents/qlearn/qtable.py
easyneuron/agents/qlearn/value.py
easyneuron/data/__init__.py
easyneuron/data/gen.py
easyneuron/data/load.py
easyneuron/exceptions/__init__.py
easyneuron/exceptions/exceptions.py
easyneuron/genetic/__init__.py
easyneuron/genetic/cross/__init__.py
easyneuron/genetic/genome/__init__.py
easyneuron/genetic/genome/base.py
easyneuron/genetic/genome/mutate.py
easyneuron/genetic/optim/__init__.py
easyneuron/genetic/optim/base.py
easyneuron/genetic/select/__init__.py
easyneuron/logging/__init__.py
easyneuron/logging/logging.py
easyneuron/math/__init__.py
easyneuron/math/distance/__init__.py
easyneuron/math/distance/distance.py
easyneuron/math/random/__init__.py
easyneuron/math/random/random.py
easyneuron/metrics/__init__.py
easyneuron/metrics/accuracy/__init__.py
easyneuron/metrics/accuracy/accuracy.py
easyneuron/metrics/loss/__init__.py
easyneuron/metrics/loss/meanerrors.py
easyneuron/neighbours/__init__.py
easyneuron/neighbours/_classes.py
easyneuron/neighbours/knearest.py
easyneuron/types/__init__.py
easyneuron/types/types.py
sandbox/__init__.py
sandbox/_classes/__init__.py
sandbox/_classes/models.py
sandbox/_testutils/__init__.py
sandbox/_testutils/gh_actions.py
sandbox/_testutils/logger.py
sandbox/agents/__init__.py
sandbox/agents/envs/__init__.py
sandbox/agents/envs/_classes.py
sandbox/agents/envs/examples.py
sandbox/agents/qlearn/__init__.py
sandbox/agents/qlearn/qtable.py
sandbox/agents/qlearn/value.py
sandbox/data/__init__.py
sandbox/data/gen.py
sandbox/data/load.py
sandbox/exceptions/__init__.py
sandbox/exceptions/exceptions.py
sandbox/genetic/__init__.py
sandboxai-0.0.1.dist-info/LICENSE
sandboxai-0.0.1.dist-info/METADATA
sandboxai-0.0.1.dist-info/WHEEL
sandboxai-0.0.1.dist-info/top_level.txt
sandboxai-0.0.1.dist-info/RECORD
